atk_common/__init__.py
atk_common/bo_logger.py
atk_common/consumer_retry_handler.py
atk_common/datetime_utils.py
atk_common/db_utils.py
atk_common/default_should_retry.py
atk_common/docker_utils.py
atk_common/env_utils.py
atk_common/error_utils.py
atk_common/file_utils.py
atk_common/hash_utils.py
atk_common/http_response_utils.py
atk_common/http_utils.py
atk_common/internal_response_utils.py
atk_common/log_utils.py
atk_common/mq_utils.py
atk_common/rabbitmq_consumer.py
atk_common/response_utils.py
atk_common/api_init/__init__.py
atk_common/api_init/docker_handler_init.py
atk_common/api_init/env_handler_init.py
atk_common/api_init/error_handler_init.py
atk_common/api_init/http_response_handler_init.py
atk_common/api_init/logger_init.py
atk_common/api_proxies/__init__.py
atk_common/api_proxies/docker_handler_proxy.py
atk_common/api_proxies/env_handler_proxy.py
atk_common/api_proxies/error_handler_proxy.py
atk_common/api_proxies/http_response_handler_proxy.py
atk_common/api_proxies/logger_proxy.py
atk_common/classes/__init__.py
atk_common/classes/bo_logger.py
atk_common/classes/bo_logger_old.py
atk_common/classes/docker_handler.py
atk_common/classes/env_handler.py
atk_common/classes/error_handler.py
atk_common/classes/http_response_handler.py
atk_common/classes/http_response_handler_old.py
atk_common/classes/rabbitmq_consumer.py
atk_common/classes/request_context.py
atk_common/enums/__init__.py
atk_common/enums/api_error_type_enum.py
atk_common/enums/camera_cabinet_type_enum.py
atk_common/enums/camera_role_enum.py
atk_common/enums/certificate_issuer_enum.py
atk_common/enums/certificate_type_enum.py
atk_common/enums/command_status_enum.py
atk_common/enums/command_status_type_enum.py
atk_common/enums/command_type_enum.py
atk_common/enums/config_reply_status_type.py
atk_common/enums/config_reply_status_type_enum.py
atk_common/enums/detection_status_enum.py
atk_common/enums/detection_status_type_enum.py
atk_common/enums/deviation_code_category_enum.py
atk_common-5.17.0.dist-info/licenses/license.txt
atk_common-5.17.0.dist-info/METADATA
atk_common-5.17.0.dist-info/WHEEL
atk_common-5.17.0.dist-info/top_level.txt
atk_common-5.17.0.dist-info/RECORD
